Metadata-Version: 1.0
Name: VTEReportsAnalysis
Version: 1.2
Summary: A Python implementation of simpleNLP algorithm
Home-page: https://github.com/ykevingrox/VTEReports
Author: Jingxian You
Author-email: jingxian.you@nhs.net
License: UNKNOWN
Platform: UNKNOWN
